apycotbot
