Metadata-Version: 1.0
Name: apycotbot
Version: 1.10.0
Summary: Apycot bot client dedicated to launch test suites
Home-page: http://www.logilab.org/project/apycot
Author: Logilab
Author-email: contact@logilab.fr
License: GPL
Platform: UNKNOWN
